PicaChu_lib/__init__.py
PicaChu_lib/pokemon.csv
PicaChu_lib/random_pokemon.py
charzr_lib/__init__.py
charzr_lib/pokemon.csv
charzr_lib/random_pokemon.py
charzr_lib-1.1.5.dist-info/METADATA
charzr_lib-1.1.5.dist-info/WHEEL
charzr_lib-1.1.5.dist-info/top_level.txt
charzr_lib-1.1.5.dist-info/RECORD
